thikuzhal/__init__.py
thikuzhal/hi.py
thikuzhal-0.1.dist-info/METADATA
thikuzhal-0.1.dist-info/WHEEL
thikuzhal-0.1.dist-info/top_level.txt
thikuzhal-0.1.dist-info/RECORD
