Metadata-Version: 2.1
Name: thikuzhal
Version: 0.1
Summary: ThiruKuzhal Test in the world
Home-page: UNKNOWN
Author: Thirumoorthy
Author-email: thirumoorthy.gmk@gmail.com
License: Mepco
Platform: UNKNOWN
